MANIFEST.in
README.rst
setup.py
django_paypal2/__init__.py
django_paypal2/admin.py
django_paypal2/settings.py
django_paypal2/urls.py
django_paypal2/views.py
django_paypal2/wsgi.py
django_paypal2.egg-info/PKG-INFO
django_paypal2.egg-info/SOURCES.txt
django_paypal2.egg-info/dependency_links.txt
django_paypal2.egg-info/requires.txt
django_paypal2.egg-info/top_level.txt
paypal/__init__.py
paypal/admin.py
paypal/apps.py
paypal/models.py
paypal/signals.py
paypal/urls.py
paypal/views.py
paypal/migrations/0001_initial.py
paypal/migrations/0002_auto_20170808_0550.py
paypal/migrations/0003_paypaltransaction_user.py
paypal/migrations/0004_paypaltransaction_uid.py
paypal/migrations/0005_auto_20180110_0330.py
paypal/migrations/0006_rename_model.py
paypal/migrations/__init__.py
paypal/templates/paypal/cancel.html
paypal/templates/paypal/return.html
paypal/tests/__init__.py
paypal/tests/test_models.py
paypal/tests/test_views.py